Workbook

Sheet Priority 25
A1: Schlieren Guard — Recommended First 25 Reach-Outs | B1: Schlieren Guard — Recommended First 25 Reach-Outs | C1: Schlieren Guard — Recommended First 25 Reach-Outs | D1: Schlieren Guard — Recommended First 25 Reach-Outs | E1: Schlieren Guard — Recommended First 25 Reach-Outs | F1: Schlieren Guard — Recommended First 25 Reach-Outs | G1: Schlieren Guard — Recommended First 25 Reach-Outs | H1: Schlieren Guard — Recommended First 25 Reach-Outs | I1: Schlieren Guard — Recommended First 25 Reach-Outs | J1: Schlieren Guard — Recommended First 25 Reach-Outs | K1: Schlieren Guard — Recommended First 25 Reach-Outs | L1: Schlieren Guard — Recommended First 25 Reach-Outs | M1: Schlieren Guard — Recommended First 25 Reach-Outs | N1: Schlieren Guard — Recommended First 25 Reach-Outs | O1: Schlieren Guard — Recommended First 25 Reach-Outs | P1: Schlieren Guard — Recommended First 25 Reach-Outs
A2: 25 FIRST-WAVE TARGETS | E2: 5 × 5 OUTREACH BATCHES | I2: 1 PAID PILOT GOAL | M2: $2,500 PROPOSED PILOT
A6: Rank | B6: Company / product | C6: Segment | D6: Why this target | E6: Buyer role | F6: Contact route | G6: Public contact | H6: Opening pitch | I6: Current build gap | J6: Score | K6: Confidence | L6: Evidence | M6: Status | N6: Last touch | O6: Owner | P6: Next step / notes
A7: ='All 40'!A6 -> 1 | B7: ='All 40'!C6&" / "&'All 40'!D6 -> Codex Data Inc. / Defined.fi | C7: ='All 40'!E6 -> Trading analytics | D7: ='All 40'!F6 -> Token discovery and execution sit in one trader workflow; Guard adds reproducible sellability evidence when token data is inconclusive. | E7: ='All 40'!H6 -> Founder/CEO; Head of Product; Partnerships | F7: ='All 40'!I6 -> Email + LinkedIn role follow-up | G7: ='All 40'!J6 -> hello@defined.fi | H7: ='All 40'!L6 -> Add an execution-verified evidence card beside Defined's token data; start with disputed/high-risk EVM tokens. | I7: ='All 40'!G6 -> Direct: Ethereum trading proof; router adapter may be needed | J7: ='All 40'!R6 -> 92 | K7: ='All 40'!S6 -> High | L7: ='All 40'!U6 -> https://play.google.com/store/apps/details?id=fi.defined | M7: Not started | O7: Erick
A8: ='All 40'!A7 -> 2 | B8: ='All 40'!C7&" / "&'All 40'!D7 -> DEXTools / DEXTools | C8: ='All 40'!E7 -> Trading analytics | D8: ='All 40'!F7 -> Already surfaces token risk and has integrated external security data; Guard can become a second-opinion evidence link rather than another score. | E8: ='All 40'!H7 -> Head of Product; API Partnerships; CTO | F8: ='All 40'!I7 -> Company email, then LinkedIn product lead | G8: ='All 40'!J7 -> info@dextools.io | H8: ='All 40'!L7 -> When DEXTScore and static scanners disagree, open a pinned BUY→SELL replay showing what actually happened. | I8: ='All 40'!G7 -> Direct: Ethereum/Uniswap-style proof | J8: ='All 40'!R7 -> 86 | K8: ='All 40'!S7 -> High | L8: ='All 40'!U7 -> https://www.dextools.io/app/en | M8: Not started | O8: Erick
A9: ='All 40'!A8 -> 3 | B9: ='All 40'!C8&" / "&'All 40'!D8 -> CryptoHub / CoinScan | C9: ='All 40'!E8 -> Trading analytics | D9: ='All 40'!F8 -> Safety features and trader analytics make a verified sell test a natural premium or trust feature. | E9: ='All 40'!H8 -> Founder; Product Lead; Partnerships | F9: ='All 40'!I8 -> Official support/business email | G9: ='All 40'!J8 -> contact@coinscan.com | H9: ='All 40'!L8 -> Embed a one-click execution proof for new EVM pairs and let users share the replay URL. | I9: ='All 40'!G8 -> Direct: Ethereum token workflow | J9: ='All 40'!R8 -> 94 | K9: ='All 40'!S8 -> High | L9: ='All 40'!U8 -> https://docs.coinscan.com/ | M9: Not started | O9: Erick
A10: ='All 40'!A9 -> 4 | B10: ='All 40'!C9&" / "&'All 40'!D9 -> Maestro Bots / Maestro | C10: ='All 40'!E9 -> Trading bot | D10: ='All 40'!F9 -> Automated sniping and cross-chain execution expose users directly to taxes, blocked sells, and route-specific failures. | E10: ='All 40'!H9 -> Founder/COO; Head of Product; Partnerships | F10: ='All 40'!I9 -> Official 24/7 support + X | G10: ='All 40'!J9 -> @MaestroBots | H10: ='All 40'!L9 -> Run Guard before a snipe or on demand; return PASS/BLOCKED, measured loss, and evidence without slowing every order. | I10: ='All 40'!G9 -> Direct on Ethereum; other chains/venues are paid adapters | J10: ='All 40'!R9 -> 90 | K10: ='All 40'!S9 -> Medium | L10: ='All 40'!U9 -> https://www.maestrobots.com/ | M10: Not started | O10: Erick
A11: ='All 40'!A10 -> 5 | B11: ='All 40'!C10&" / "&'All 40'!D10 -> Unibot / Unibot X | C11: ='All 40'!E10 -> Trading bot | D11: ='All 40'!F10 -> Ethereum/Base/Arbitrum trading and token scan surfaces create a direct place for execution-verified risk. | E11: ='All 40'!H10 -> CTO; Product Lead; Partnerships | F11: ='All 40'!I10 -> Official X DM + in-product Telegram support | G11: ='All 40'!J10 -> @TeamUnibot | H11: ='All 40'!L10 -> Use Guard as a pre-trade second opinion for tokens whose scan is uncertain or whose route recently failed. | I11: ='All 40'!G10 -> Direct: Ethereum; Base/Arbitrum adapter by pilot | J11: ='All 40'!R10 -> 86 | K11: ='All 40'!S10 -> Medium | L11: ='All 40'!U10 -> https://x.com/TeamUnibot | M11: Not started | O11: Erick
A12: ='All 40'!A11 -> 6 | B12: ='All 40'!C11&" / "&'All 40'!D11 -> BANANAGUN LTD / Banana Gun | C12: ='All 40'!E11 -> Trading bot | D12: ='All 40'!F11 -> Snipe and swap users need immediate evidence that a token can be sold under current state and route conditions. | E12: ='All 40'!H11 -> Founder; Product/Security Lead; Partnerships | F12: ='All 40'!I11 -> Official X/LinkedIn company page | G12: ='All 40'!J11 -> @BananaGunBot | H12: ='All 40'!L11 -> Add execution proof to the existing 'safe trade' promise: tested route, observed loss, and replay when blocked. | I12: ='All 40'!G11 -> Direct: Ethereum; Base/Blast adapters by pilot | J12: ='All 40'!R11 -> 86 | K12: ='All 40'!S11 -> Medium | L12: ='All 40'!U11 -> https://www.linkedin.com/company/bananagunbot | M12: Not started | O12: Erick
A13: ='All 40'!A12 -> 7 | B13: ='All 40'!C12&" / "&'All 40'!D12 -> BullX / BullX Turbo / BullX | C13: ='All 40'!E12 -> Trading terminal | D13: ='All 40'!F12 -> Multichain token discovery and fast execution make failed sells and hidden loss directly relevant to retention and trust. | E13: ='All 40'!H12 -> Founder; Head of Product; Partnerships | F13: ='All 40'!I12 -> Official X DM + Discord linked from product | G13: ='All 40'!J12 -> @bullx_io | H13: ='All 40'!L12 -> Pilot Guard on BullX Turbo for one EVM chain; only deep-simulate failures or user-requested explanations. | I13: ='All 40'!G12 -> Requires BullX EVM route adapter | J13: ='All 40'!R12 -> 86 | K13: ='All 40'!S12 -> Medium | L13: ='All 40'!U12 -> https://x.com/bullx_io | M13: Not started | O13: Erick
A14: ='All 40'!A13 -> 8 | B14: ='All 40'!C13&" / "&'All 40'!D13 -> GMGN / GMGN.AI | C14: ='All 40'!E13 -> Trading terminal | D14: ='All 40'!F13 -> GMGN already audits token risk and executes trades across Ethereum, Base, and BSC; replayable evidence is the differentiator. | E14: ='All 40'!H13 -> Head of Product; Security Product; Partnerships | F14: ='All 40'!I13 -> Official Telegram or X | G14: ='All 40'!J13 -> t.me/gmgnai | @gmgnai | H14: ='All 40'!L13 -> Do not replace GMGN's audit. Add an 'execution verified' result for contested tokens and high-value orders. | I14: ='All 40'!G13 -> Direct concept; venue-specific adapter required | J14: ='All 40'!R13 -> 86 | K14: ='All 40'!S13 -> High | L14: ='All 40'!U13 -> https://gmgn.ai/static/tos.html | M14: Not started | O14: Erick
A15: ='All 40'!A14 -> 9 | B15: ='All 40'!C14&" / "&'All 40'!D14 -> Tiny Astro / Photon | C15: ='All 40'!E14 -> Trading terminal | D15: ='All 40'!F14 -> Fast token discovery and trading exposes the exact new-token uncertainty Guard measures. | E15: ='All 40'!H14 -> Founder; Product Lead; Partnerships | F15: ='All 40'!I14 -> Official X DM | G15: ='All 40'!J14 -> @tradewithPhoton | H15: ='All 40'!L14 -> Offer a one-chain pilot that shows observed round-trip loss and a replay link before users size up a trade. | I15: ='All 40'!G14 -> Ethereum version is adjacent; confirm current route | J15: ='All 40'!R14 -> 86 | K15: ='All 40'!S14 -> Medium | L15: ='All 40'!U14 -> https://x.com/tradewithPhoton | M15: Not started | O15: Erick
A16: ='All 40'!A15 -> 10 | B16: ='All 40'!C15&" / "&'All 40'!D15 -> Clanker / Clanker | C16: ='All 40'!E15 -> Token launch platform | D16: ='All 40'!F15 -> A launch protocol can publish execution-verified sellability immediately after pool creation. | E16: ='All 40'!H15 -> Core team; Protocol/Product Lead | F16: ='All 40'!I15 -> Official project email + Farcaster/X | G16: ='All 40'!J15 -> intern@clanker.world | H16: ='All 40'!L15 -> Make 'Guard verified at block X' an optional launch badge and evidence page for every new Base token. | I16: ='All 40'!G15 -> Requires Base/Clanker pool adapter | J16: ='All 40'!R15 -> 88 | K16: ='All 40'!S15 -> High | L16: ='All 40'!U15 -> https://clanker.world/clanker/0xa1888e697da3aeac839398408922db6fc0728b07 | M16: Not started | O16: Erick
A17: ='All 40'!A16 -> 11 | B17: ='All 40'!C16&" / "&'All 40'!D16 -> TrustSwap Inc. / Team.Finance | C17: ='All 40'!E16 -> Token infrastructure | D17: ='All 40'!F16 -> Token creation, locks, vesting, and white-label services create a natural verification checkpoint before a project goes live. | E17: ='All 40'!H16 -> Business Development & Partnerships Manager | F17: ='All 40'!I16 -> Sales email or schedule-a-call form | G17: ='All 40'!J16 -> info@team.finance | H17: ='All 40'!L16 -> Add an optional post-launch Guard certificate: exact pool, exact block, observed sell result, and replay bundle. | I17: ='All 40'!G16 -> Requires buyer-selected chain/venue adapter | J17: ='All 40'!R16 -> 92 | K17: ='All 40'!S16 -> High | L17: ='All 40'!U16 -> https://www.team.finance/contact | M17: Not started | O17: Erick
A18: ='All 40'!A17 -> 12 | B18: ='All 40'!C17&" / "&'All 40'!D17 -> DxSale Network / DxSale | C18: ='All 40'!E17 -> Token launch platform | D18: ='All 40'!F17 -> Projects mint, launch, and lock liquidity on one platform; verified trade execution can be a paid launch add-on. | E18: ='All 40'!H17 -> Founder; Product Lead | F18: ='All 40'!I17 -> Founder email from official docs | G18: ='All 40'!J17 -> dennis@dxsale.network | H18: ='All 40'!L17 -> Offer execution verification as an optional launch-package certificate, not investment approval. | I18: ='All 40'!G17 -> Likely requires BNB/EVM venue adapter | J18: ='All 40'!R17 -> 92 | K18: ='All 40'!S17 -> High | L18: ='All 40'!U17 -> https://docs.dxsale.network/what-is-dxsale/team-contact-us | M18: Not started | O18: Erick
... A31: ='All 40'!A30 -> 25 | B31: ='All 40'!C30&" / "&'All 40'!D30 -> thirdweb / thirdweb | C31: ='All 40'!E30 -> Developer infrastructure | D31: ='All 40'!F30 -> Wallet, token, transaction, and API products could distribute Guard to many builders if packaged as a developer primitive. | E31: ='All 40'!H30 -> Product Partnerships; Head of Transactions/Wallets | F31: ='All 40'!I30 -> Official contact-sales form | G31: ='All 40'!J30 -> Contact form | H31: ='All 40'!L30 -> Offer a Guard preflight component for apps launching or trading ERC-20s through thirdweb infrastructure. | I31: ='All 40'!G30 -> Requires productized endpoint and one venue adapter | J31: ='All 40'!R30 -> 78 | K31: ='All 40'!S30 -> High | L31: ='All 40'!U30 -> https://thirdweb.com/contact-us | M31: Not started | O31: Erick

Sheet All 40
A1: Schlieren Guard — 40 Verified Prospect Targets | B1: Schlieren Guard — 40 Verified Prospect Targets | C1: Schlieren Guard — 40 Verified Prospect Targets | D1: Schlieren Guard — 40 Verified Prospect Targets | E1: Schlieren Guard — 40 Verified Prospect Targets | F1: Schlieren Guard — 40 Verified Prospect Targets | G1: Schlieren Guard — 40 Verified Prospect Targets | H1: Schlieren Guard — 40 Verified Prospect Targets | I1: Schlieren Guard — 40 Verified Prospect Targets | J1: Schlieren Guard — 40 Verified Prospect Targets | K1: Schlieren Guard — 40 Verified Prospect Targets | L1: Schlieren Guard — 40 Verified Prospect Targets | M1: Schlieren Guard — 40 Verified Prospect Targets | N1: Schlieren Guard — 40 Verified Prospect Targets | O1: Schlieren Guard — 40 Verified Prospect Targets | P1: Schlieren Guard — 40 Verified Prospect Targets | Q1: Schlieren Guard — 40 Verified Prospect Targets | R1: Schlieren Guard — 40 Verified Prospect Targets | S1: Schlieren Guard — 40 Verified Prospect Targets | T1: Schlieren Guard — 40 Verified Prospect Targets | U1: Schlieren Guard — 40 Verified Prospect Targets | V1: Schlieren Guard — 40 Verified Prospect Targets
A2: Ranking objective: fastest credible paid pilot. Scores are formula-driven; recommendation order also reflects current Ethereum/Uniswap V2 proof and sales-cycle judgment.
A5: Rank | B5: Wave | C5: Company | D5: Product | E5: Segment | F5: Why Guard fits | G5: Current demo fit / gap | H5: Best buyer role | I5: Primary contact path | J5: Public contact detail | K5: Contact URL | L5: Pitch angle | M5: Fit (0-5) | N5: Urgency (0-5) | O5: Contactability (0-5) | P5: Pilot simplicity (0-5) | Q5: Conflict penalty (0-5) | R5: Priority score | S5: Contact confidence | T5: Product source | U5: Contact source | V5: Notes
A6: 1 | B6: First 25 | C6: Codex Data Inc. | D6: Defined.fi | E6: Trading analytics | F6: Token discovery and execution sit in one trader workflow; Guard adds reproducible sellability evidence when token data is inconclusive. | G6: Direct: Ethereum trading proof; router adapter may be needed | H6: Founder/CEO; Head of Product; Partnerships | I6: Email + LinkedIn role follow-up | J6: hello@defined.fi | K6: https://www.defined.fi/ | L6: Add an execution-verified evidence card beside Defined's token data; start with disputed/high-risk EVM tokens. | M6: 5 | N6: 5 | O6: 5 | P6: 4 | Q6: 2 | R6: =M6*7+N6*5+O6*4+P6*4-Q6*2 -> 92 | S6: High | T6: https://www.codex.io/case-studies/defined | U6: https://play.google.com/store/apps/details?id=fi.defined | V6: Do not pitch a replacement for Codex data; pitch an evidence layer for exceptions.
A7: 2 | B7: First 25 | C7: DEXTools | D7: DEXTools | E7: Trading analytics | F7: Already surfaces token risk and has integrated external security data; Guard can become a second-opinion evidence link rather than another score. | G7: Direct: Ethereum/Uniswap-style proof | H7: Head of Product; API Partnerships; CTO | I7: Company email, then LinkedIn product lead | J7: info@dextools.io | K7: mailto:info@dextools.io | L7: When DEXTScore and static scanners disagree, open a pinned BUY→SELL replay showing what actually happened. | M7: 5 | N7: 5 | O7: 4 | P7: 4 | Q7: 3 | R7: =M7*7+N7*5+O7*4+P7*4-Q7*2 -> 86 | S7: High | T7: https://info.dextools.io/dextools-api-v2-powering-the-future-of-defi/ | U7: https://www.dextools.io/app/en | V7: Mention existing Quick Intel integration; sell complementary adjudication, not displacement.
A8: 3 | B8: First 25 | C8: CryptoHub | D8: CoinScan | E8: Trading analytics | F8: Safety features and trader analytics make a verified sell test a natural premium or trust feature. | G8: Direct: Ethereum token workflow | H8: Founder; Product Lead; Partnerships | I8: Official support/business email | J8: contact@coinscan.com | K8: mailto:contact@coinscan.com | L8: Embed a one-click execution proof for new EVM pairs and let users share the replay URL. | M8: 5 | N8: 5 | O8: 5 | P8: 4 | Q8: 1 | R8: =M8*7+N8*5+O8*4+P8*4-Q8*2 -> 94 | S8: High | T8: https://docs.coinscan.com/ | U8: https://docs.coinscan.com/ | V8: Small enough for founder-led decision; one of the cleanest paid-pilot prospects.
A9: 4 | B9: First 25 | C9: Maestro Bots | D9: Maestro | E9: Trading bot | F9: Automated sniping and cross-chain execution expose users directly to taxes, blocked sells, and route-specific failures. | G9: Direct on Ethereum; other chains/venues are paid adapters | H9: Founder/COO; Head of Product; Partnerships | I9: Official 24/7 support + X | J9: @MaestroBots | K9: https://x.com/MaestroBots | L9: Run Guard before a snipe or on demand; return PASS/BLOCKED, measured loss, and evidence without slowing every order. | M9: 5 | N9: 5 | O9: 4 | P9: 4 | Q9: 1 | R9: =M9*7+N9*5+O9*4+P9*4-Q9*2 -> 90 | S9: Medium | T9: https://www.maestrobots.com/ | U9: https://www.maestrobots.com/ | V9: Ask support to route a business-integration request; never send keys or wallet information.
A10: 5 | B10: First 25 | C10: Unibot | D10: Unibot X | E10: Trading bot | F10: Ethereum/Base/Arbitrum trading and token scan surfaces create a direct place for execution-verified risk. | G10: Direct: Ethereum; Base/Arbitrum adapter by pilot | H10: CTO; Product Lead; Partnerships | I10: Official X DM + in-product Telegram support | J10: @TeamUnibot | K10: https://x.com/TeamUnibot | L10: Use Guard as a pre-trade second opinion for tokens whose scan is uncertain or whose route recently failed. | M10: 5 | N10: 5 | O10: 3 | P10: 4 | Q10: 1 | R10: =M10*7+N10*5+O10*4+P10*4-Q10*2 -> 86 | S10: Medium | T10: https://unibot.app/ | U10: https://x.com/TeamUnibot | V10: Reference the current token-scan feature and prior router-security sensitivity; keep the tone technical.
A11: 6 | B11: First 25 | C11: BANANAGUN LTD | D11: Banana Gun | E11: Trading bot | F11: Snipe and swap users need immediate evidence that a token can be sold under current state and route conditions. | G11: Direct: Ethereum; Base/Blast adapters by pilot | H11: Founder; Product/Security Lead; Partnerships | I11: Official X/LinkedIn company page | J11: @BananaGunBot | K11: https://x.com/BananaGunBot | L11: Add execution proof to the existing 'safe trade' promise: tested route, observed loss, and replay when blocked. | M11: 5 | N11: 5 | O11: 3 | P11: 4 | Q11: 1 | R11: =M11*7+N11*5+O11*4+P11*4-Q11*2 -> 86 | S11: Medium | T11: https://www.linkedin.com/company/bananagunbot | U11: https://www.linkedin.com/company/bananagunbot | V11: Legal email is published but is not the right first sales route.
A12: 7 | B12: First 25 | C12: BullX | D12: BullX Turbo / BullX | E12: Trading terminal | F12: Multichain token discovery and fast execution make failed sells and hidden loss directly relevant to retention and trust. | G12: Requires BullX EVM route adapter | H12: Founder; Head of Product; Partnerships | I12: Official X DM + Discord linked from product | J12: @bullx_io | K12: https://x.com/bullx_io | L12: Pilot Guard on BullX Turbo for one EVM chain; only deep-simulate failures or user-requested explanations. | M12: 5 | N12: 5 | O12: 3 | P12: 4 | Q12: 1 | R12: =M12*7+N12*5+O12*4+P12*4-Q12*2 -> 86 | S12: Medium | T12: https://bullx.io/ | U12: https://x.com/bullx_io | V12: Confirm the current EVM venue before finalizing acceptance criteria.
A13: 8 | B13: First 25 | C13: GMGN | D13: GMGN.AI | E13: Trading terminal | F13: GMGN already audits token risk and executes trades across Ethereum, Base, and BSC; replayable evidence is the differentiator. | G13: Direct concept; venue-specific adapter required | H13: Head of Product; Security Product; Partnerships | I13: Official Telegram or X | J13: t.me/gmgnai | @gmgnai | K13: https://t.me/gmgnai | L13: Do not replace GMGN's audit. Add an 'execution verified' result for contested tokens and high-value orders. | M13: 5 | N13: 5 | O13: 4 | P13: 4 | Q13: 3 | R13: =M13*7+N13*5+O13*4+P13*4-Q13*2 -> 86 | S13: High | T13: https://gmgn.ai/ | U13: https://gmgn.ai/static/tos.html | V13: Strong need but meaningful overlap; insist on paid evaluation or data partnership terms.
A14: 9 | B14: First 25 | C14: Tiny Astro | D14: Photon | E14: Trading terminal | F14: Fast token discovery and trading exposes the exact new-token uncertainty Guard measures. | G14: Ethereum version is adjacent; confirm current route | H14: Founder; Product Lead; Partnerships | I14: Official X DM | J14: @tradewithPhoton | K14: https://x.com/tradewithPhoton | L14: Offer a one-chain pilot that shows observed round-trip loss and a replay link before users size up a trade. | M14: 5 | N14: 5 | O14: 3 | P14: 4 | Q14: 1 | R14: =M14*7+N14*5+O14*4+P14*4-Q14*2 -> 86 | S14: Medium | T14: https://photon-sol.tinyastro.io/ | U14: https://x.com/tradewithPhoton | V14: Lead with the EVM product, not the better-known Solana surface.
A15: 10 | B15: First 25 | C15: Clanker | D15: Clanker | E15: Token launch platform | F15: A launch protocol can publish execution-verified sellability immediately after pool creation. | G15: Requires Base/Clanker pool adapter | H15: Core team; Protocol/Product Lead | I15: Official project email + Farcaster/X | J15: intern@clanker.world | K15: mailto:intern@clanker.world | L15: Make 'Guard verified at block X' an optional launch badge and evidence page for every new Base token. | M15: 5 | N15: 5 | O15: 4 | P15: 3 | Q15: 0 | R15: =M15*7+N15*5+O15*4+P15*4-Q15*2 -> 88 | S15: High | T15: https://clanker.world/docs | U15: https://clanker.world/clanker/0xa1888e697da3aeac839398408922db6fc0728b07 | V15: Excellent design partner if it will fund Base and its current pool mechanics.
A16: 11 | B16: First 25 | C16: TrustSwap Inc. | D16: Team.Finance | E16: Token infrastructure | F16: Token creation, locks, vesting, and white-label services create a natural verification checkpoint before a project goes live. | G16: Requires buyer-selected chain/venue adapter | H16: Business Development & Partnerships Manager | I16: Sales email or schedule-a-call form | J16: info@team.finance | K16: mailto:info@team.finance | L16: Add an optional post-launch Guard certificate: exact pool, exact block, observed sell result, and replay bundle. | M16: 5 | N16: 5 | O16: 5 | P16: 3 | Q16: 0 | R16: =M16*7+N16*5+O16*4+P16*4-Q16*2 -> 92 | S16: High | T16: https://www.team.finance/ | U16: https://www.team.finance/contact | V16: Official page names two BD/partnership managers; route directly to that team.
A17: 12 | B17: First 25 | C17: DxSale Network | D17: DxSale | E17: Token launch platform | F17: Projects mint, launch, and lock liquidity on one platform; verified trade execution can be a paid launch add-on. | G17: Likely requires BNB/EVM venue adapter | H17: Founder; Product Lead | I17: Founder email from official docs | J17: dennis@dxsale.network | K17: mailto:dennis@dxsale.network | L17: Offer execution verification as an optional launch-package certificate, not investment approval. | M17: 5 | N17: 5 | O17: 5 | P17: 3 | Q17: 0 | R17: =M17*7+N17*5+O17*4+P17*4-Q17*2 -> 92 | S17: High | T17: https://docs.dxsale.network/what-is-dxsale/readme | U17: https://docs.dxsale.network/what-is-dxsale/team-contact-us | V17: Define the liability language carefully: observed test, not warranty or endorsement.
... A45: 40 | B45: Second wave | C45: Coinbase | D45: Coinbase Wallet / Base App | E45: Wallet + developer platform | F45: Strong Base distribution and partner program, but enterprise procurement and current scope make this a late-stage target. | G45: Requires Base adapter, production API, controls, and scale | H45: Wallet Product Partnerships; CDP Partner Network | I45: Official Wallet SDK partner application | J45: Apply to partner program | K45: https://www.coinbase.com/developer-platform/products/wallet-sdk | L45: After a Base design partner exists, propose execution-verified token evidence for Base App and CDP wallet builders. | M45: 4 | N45: 4 | O45: 2 | P45: 2 | Q45: 3 | R45: =M45*7+N45*5+O45*4+P45*4-Q45*2 -> 58 | S45: High | T45: https://www.coinbase.com/developer-platform | U45: https://www.coinbase.com/developer-platform/products/wallet-sdk | V45: Do not approach first; obtain Clanker or another Base proof case before Coinbase.

Sheet Outreach Plays
A1: Guard Outreach Plays — What to Say and What to Ask For | B1: Guard Outreach Plays — What to Say and What to Ask For | C1: Guard Outreach Plays — What to Say and What to Ask For | D1: Guard Outreach Plays — What to Say and What to Ask For | E1: Guard Outreach Plays — What to Say and What to Ask For | F1: Guard Outreach Plays — What to Say and What to Ask For
A2: Objective: sell a tightly scoped paid design-partner pilot before production build. Lead with proof from the current prototype, disclose the current Ethereum/Uniswap V2 boundary, and let the buyer fund the next chain or venue adapter.
A5: Segment | B5: Lead sentence | C5: Proof to attach | D5: Specific ask | E5: Buyer benefit | F5: Do not claim
A6: Trading bot / terminal | B6: You already help users find and execute new-token trades. Guard can test whether the token can be sold under pinned state before the user sizes up. | C6: Blocked-sell replay + measured-loss example | D6: 20-minute technical review; $2,500 one-chain pilot | E6: Fewer failed trades, fewer disputes, visible proof | F6: Do not say Guard guarantees safety or catches every honeypot.
A7: Token analytics | B7: Your users already see scores and flags. Guard adds the missing evidence: the exact trade scenario, outcome, block, and replay. | C7: Side-by-side scanner disagreement example | D7: Pilot an 'execution verified' card on selected EVM tokens | E7: Differentiated trust layer and shareable results | F7: Do not say competitors only use databases; several simulate.
A8: Wallet | B8: Before a user signs an obscure-token swap, Guard can run an on-demand round trip and explain the observed failure without becoming a default hard blocker. | C8: Normal trade + blocked trade UI mock | D8: Pilot the 'Explain token risk' action on one chain | E8: User protection without slowing every transaction | F8: Do not promise sub-second production latency today.
A9: Launch platform | B9: You can verify a token's actual sell path immediately after launch and publish the pinned evidence beside the project. | C9: Launch badge mock + evidence bundle | D9: Paid adapter for the platform's primary chain/DEX | E9: Premium launch add-on and reduced reputational risk | F9: Do not call the badge an audit, endorsement, or warranty.
A10: Swap / routing API | B10: After your router selects a path, Guard can return optional risk metadata: observed sell result, round-trip loss, evidence URL, and freshness block. | C10: Mock quote response with guard object | D10: One route family, one chain, one integration endpoint | E10: Fewer toxic-token routes and better support evidence | F10: Do not offer broad multi-chain coverage before it is funded.
A11: Security provider | B11: Use Guard as an adjudication/evidence layer when your risk engine flags an asset or scanners disagree. | C11: Replayable failure bundle | D11: Paid data partnership or escalation workflow | E11: Higher-confidence cases and defensible evidence | F11: Do not hand over proprietary implementation without commercial terms.
A14: Recommended pilot offer
A15: Price | B15: $2,500 total; $1,250 non-refundable deposit credited to delivery
A16: Term | B16: 60 days
A17: Scope | B17: One chain, one venue/router, BUY→APPROVE→SELL, measured loss, evidence bundle, one integration endpoint
A18: Acceptance | B18: Named test cases, response contract, evidence fields, and latency target agreed before payment
A19: Boundary | B19: Observed execution result at pinned state—not an audit, guarantee, or universal honeypot verdict
A20: Commercial hook | B20: Pilot payment credited toward a production agreement if both parties continue
A23: Four-touch cadence
A24: Timing | B24: Channel | C24: Purpose | D24: Send | E24: Success signal | F24: Stop condition
A25: Day 0 | B25: Email or official DM | C25: Earn the technical review | D25: 90-word message + one proof link | E25: Correct owner introduced or meeting offered | F25: No attachments larger than one page
A26: Day 2 | B26: LinkedIn/X role follow-up | C26: Route to buyer | D26: One sentence referencing Day 0 | E26: Named product/security owner | F26: Do not paste full pitch again
A27: Day 6 | B27: Email/DM | C27: Create urgency with evidence | D27: New blocked/high-loss example relevant to their product | E27: Technical questions or data request | F27: If generic praise only, ask directly about paid pilot
A28: Day 12 | B28: Email | C28: Close the loop | D28: Specific $2,500 pilot and two time slots | E28: Pricing discussion or clear no | F28: No response: move to second wave
A31: Initial message template
A32: Subject: Can Guard verify the trade before your user makes it? [Company] already helps users [discover/launch/route] new tokens. Guard adds a different kind of risk evidence: it runs a standardized BUY→APPROVE→SELL scenario against pinned EVM state, reports the observed round-trip loss or blocked sell, and produces a replayable evidence bundle. The current prototype is proven on Ethereum/Uniswap V2. I am looking for one design partner to fund a 60-day, one-chain/one-venue integration—not asking you to buy an unfinished broad platform. Would you give me 20 minutes to show the blocked-sell replay and decide whether a $2,500 pilot solves a real problem for [product]? Erick Turner Sounder Solutions LLC

Sheet Scoring & Sources
A1: Scoring, Decision Rules, and Research Notes | B1: Scoring, Decision Rules, and Research Notes | C1: Scoring, Decision Rules, and Research Notes | D1: Scoring, Decision Rules, and Research Notes | E1: Scoring, Decision Rules, and Research Notes | F1: Scoring, Decision Rules, and Research Notes
A3: Criterion | B3: Weight | C3: 0 | D3: 3 | E3: 5 | F3: Purpose
A4: Product fit | B4: 7 | C4: No natural Guard surface | D4: Adjacent workflow | E4: Direct token discovery/trade/launch surface | F4: Does the product have a place to use the result?
A5: Urgency | B5: 5 | C5: No visible pain | D5: General security need | E5: Direct exposure to new-token trade failure | F5: Will the problem command attention now?
A6: Contactability | B6: 4 | C6: No verified route | D6: Official support/community only | E6: Published business/partnership route | F6: Can Erick reach a decision owner cheaply?
A7: Pilot simplicity | B7: 4 | C7: Requires broad platform build | D7: One adapter plus endpoint | E7: Current proof maps closely | F7: Can one customer fund a bounded build?
A8: Competitive conflict | B8: -2 | C8: No overlap | D8: Some overlapping risk data | E8: Direct scanner/simulation competitor | F8: Will they buy, or only learn from us?
A11: Formula: Fit×7 + Urgency×5 + Contactability×4 + Pilot simplicity×4 − Competitive conflict×2
A14: Decision rule | B14: Meaning | C14: Action | D14: Metric | E14: Threshold | F14: Notes
A15: Money > interest | B15: Compliments and LOIs do not validate willingness to pay | C15: Ask for deposit after technical fit is confirmed | D15: Paid pilots | E15: 1 | F15: One paid pilot authorizes only the contracted build
A16: Five batches | B16: Avoid burning the whole market with one weak message | C16: Send 5, learn, revise, repeat | D16: Substantive replies | E16: 5 | F16: A substantive reply includes a buyer, technical question, or meeting
A17: Two follow-ups | B17: Most first messages will be missed | C17: Follow on Day 2 and Day 6; close Day 12 | D17: Touches per account | E17: 4 | F17: Stop after final close-the-loop unless invited
A18: No speculative build | B18: Buyer selects the next chain, venue, and endpoint | C18: No production work before deposit | D18: Unfunded build hours | E18: 0 | F18: Demo packaging is allowed; platform build is not
A19: Kill/revise gate | B19: Poor response means offer/segment is wrong | C19: Revise after First 25 before Second 15 | D19: Pricing discussions | E19: 1 | F19: Zero pricing discussions is a failed first-wave offer
A22: Research limitations
A23: Official community channels can be impersonated. Start from the exact website or documented handle in the row. | B23: Official community channels can be impersonated. Start from the exact website or documented handle in the row. | C23: Official community channels can be impersonated. Start from the exact website or documented handle in the row. | D23: Official community channels can be impersonated. Start from the exact website or documented handle in the row. | E23: Official community channels can be impersonated. Start from the exact website or documented handle in the row. | F23: Official community channels can be impersonated. Start from the exact website or documented handle in the row.
A24: Some crypto companies publish support/community routes rather than a sales email; these rows have Medium contact confidence. | B24: Some crypto companies publish support/community routes rather than a sales email; these rows have Medium contact confidence. | C24: Some crypto companies publish support/community routes rather than a sales email; these rows have Medium contact confidence. | D24: Some crypto companies publish support/community routes rather than a sales email; these rows have Medium contact confidence. | E24: Some crypto companies publish support/community routes rather than a sales email; these rows have Medium contact confidence. | F24: Some crypto companies publish support/community routes rather than a sales email; these rows have Medium contact confidence.
A25: Guard's present proof is Ethereum/Uniswap V2. Base, BNB Chain, V3, aggregators, and wallet routes must be buyer-funded pilot scope. | B25: Guard's present proof is Ethereum/Uniswap V2. Base, BNB Chain, V3, aggregators, and wallet routes must be buyer-funded pilot scope. | C25: Guard's present proof is Ethereum/Uniswap V2. Base, BNB Chain, V3, aggregators, and wallet routes must be buyer-funded pilot scope. | D25: Guard's present proof is Ethereum/Uniswap V2. Base, BNB Chain, V3, aggregators, and wallet routes must be buyer-funded pilot scope. | E25: Guard's present proof is Ethereum/Uniswap V2. Base, BNB Chain, V3, aggregators, and wallet routes must be buyer-funded pilot scope. | F25: Guard's present proof is Ethereum/Uniswap V2. Base, BNB Chain, V3, aggregators, and wallet routes must be buyer-funded pilot scope.
A26: The Guard result is an observed scenario at pinned state, not an audit, investment endorsement, or universal honeypot verdict. | B26: The Guard result is an observed scenario at pinned state, not an audit, investment endorsement, or universal honeypot verdict. | C26: The Guard result is an observed scenario at pinned state, not an audit, investment endorsement, or universal honeypot verdict. | D26: The Guard result is an observed scenario at pinned state, not an audit, investment endorsement, or universal honeypot verdict. | E26: The Guard result is an observed scenario at pinned state, not an audit, investment endorsement, or universal honeypot verdict. | F26: The Guard result is an observed scenario at pinned state, not an audit, investment endorsement, or universal honeypot verdict.
A27: Company activity and staff roles change quickly. Recheck the official route immediately before sending. | B27: Company activity and staff roles change quickly. Recheck the official route immediately before sending. | C27: Company activity and staff roles change quickly. Recheck the official route immediately before sending. | D27: Company activity and staff roles change quickly. Recheck the official route immediately before sending. | E27: Company activity and staff roles change quickly. Recheck the official route immediately before sending. | F27: Company activity and staff roles change quickly. Recheck the official route immediately before sending.
A30: Core source set (row-level sources are on All 40)
A31: DEXTools | B31: https://www.dextools.io/app/en | C31: Defined / Codex | D31: https://www.codex.io/case-studies/defined | E31: CoinScan | F31: https://docs.coinscan.com/
A32: DEX Screener | B32: https://docs.dexscreener.com/ | C32: GeckoTerminal | D32: https://www.geckoterminal.com/ad-policy | E32: Birdeye Data | F32: https://birdeye.so/data-api/contact
A33: TokenPocket | B33: https://www.tokenpocket.pro/en/about | C33: Team.Finance | D33: https://www.team.finance/contact | E33: LI.FI | F33: https://docs.li.fi/introduction/integrating-lifi/partnership-opportunities
A34: Quick Intel | B34: https://docs.quickintel.io/resources/support-and-team-contacts | C34: Webacy | D34: https://docs.webacy.com/api-reference/introduction | E34: Hypernative | F34: https://www.hypernative.io/about
A35: 1inch | B35: https://business.1inch.com/enterprise | C35: OpenOcean | D35: https://docs.openocean.finance/docs/swap-api/api-pricing-and-access | E35: Clanker | F35: https://clanker.world/docs
